server.py
context7_mcp_python-1.0.4.dist-info/licenses/LICENSE
context7_mcp_python-1.0.4.dist-info/METADATA
context7_mcp_python-1.0.4.dist-info/WHEEL
context7_mcp_python-1.0.4.dist-info/entry_points.txt
context7_mcp_python-1.0.4.dist-info/top_level.txt
context7_mcp_python-1.0.4.dist-info/RECORD
