Metadata-Version: 2.4
Name: context7-mcp-python
Version: 1.0.4
Summary: Context7 MCP 服务器 - Python 实现，提供最新的库文档和代码示例
Author-email: noimank <noimank@example.com>
Maintainer-email: noimank <noimank@example.com>
License: MIT
Project-URL: Homepage, https://github.com/noimank/context7-mcp-python
Project-URL: Documentation, https://github.com/noimank/context7-mcp-python#readme
Project-URL: Repository, https://github.com/noimank/context7-mcp-python
Project-URL: Issues, https://github.com/noimank/context7-mcp-python/issues
Keywords: mcp,context7,documentation,api,server
Classifier: Development Status :: 4 - Beta
Classifier: Intended Audience :: Developers
Classifier: License :: OSI Approved :: MIT License
Classifier: Operating System :: OS Independent
Classifier: Programming Language :: Python :: 3
Classifier: Programming Language :: Python :: 3.8
Classifier: Programming Language :: Python :: 3.9
Classifier: Programming Language :: Python :: 3.10
Classifier: Programming Language :: Python :: 3.11
Classifier: Programming Language :: Python :: 3.12
Classifier: Topic :: Software Development :: Libraries :: Python Modules
Classifier: Topic :: Internet :: WWW/HTTP :: HTTP Servers
Classifier: Topic :: Documentation
Requires-Python: >=3.8
License-File: LICENSE
Requires-Dist: httpx>=0.23.0
Requires-Dist: pydantic>=2.0.0
Requires-Dist: mcp>=1.0.0
Provides-Extra: dev
Requires-Dist: pytest>=7.0.0; extra == "dev"
Requires-Dist: pytest-asyncio>=0.21.0; extra == "dev"
Requires-Dist: black>=23.0.0; extra == "dev"
Requires-Dist: isort>=5.12.0; extra == "dev"
Requires-Dist: flake8>=6.0.0; extra == "dev"
Requires-Dist: mypy>=1.0.0; extra == "dev"
Requires-Dist: pre-commit>=3.0.0; extra == "dev"
Provides-Extra: test
Requires-Dist: pytest>=7.0.0; extra == "test"
Requires-Dist: pytest-asyncio>=0.21.0; extra == "test"
Requires-Dist: pytest-cov>=4.0.0; extra == "test"
Requires-Dist: httpx>=0.23.0; extra == "test"
Dynamic: license-file
